LICENSE
MANIFEST.in
README.md
setup.py
sentry_twilio/__init__.py
sentry_twilio/models.py
sentry_twilio.egg-info/PKG-INFO
sentry_twilio.egg-info/SOURCES.txt
sentry_twilio.egg-info/dependency_links.txt
sentry_twilio.egg-info/entry_points.txt
sentry_twilio.egg-info/not-zip-safe
sentry_twilio.egg-info/requires.txt
sentry_twilio.egg-info/top_level.txt