Metadata-Version: 1.0
Name: sentry-twilio
Version: 0.1.0
Summary: A plugin for Sentry which sends SMS notifications via Twilio
Home-page: https://github.com/mattrobenolt/sentry-twilio
Author: Matt Robenolt
Author-email: matt@ydekproductons.com
License: BSD
Platform: UNKNOWN
Classifier: Framework :: Django
Classifier: Intended Audience :: Developers
Classifier: Intended Audience :: System Administrators
Classifier: Operating System :: OS Independent
Classifier: Topic :: Software Development
